{
  "$schema": "https://developer.microsoft.com/json-schemas/spfx-build/spfx-serve.schema.json",
  "port": 4321,
  "https": true,
  "serveConfigurations": {
    "default": {
      "pageUrl": "https://{tenantDomain}/SitePages/myPage.aspx",
      "customActions": {
        "4455576d-9f4b-46e8-a035-6fc151425cae": {
          "location": "ClientSideExtension.ApplicationCustomizer",
          "properties": {
            "testMessage": "Test message"
          }
        }
      }
    },
    "appcustomizer1": {
      "pageUrl": "https://{tenantDomain}/SitePages/myPage.aspx",
      "customActions": {
        "4455576d-9f4b-46e8-a035-6fc151425cae": {
          "location": "ClientSideExtension.ApplicationCustomizer",
          "properties": {
            "testMessage": "Test message"
          }
        }
      }
    }
  }
}
